modern_pylogging/__init__.py
modern_pylogging/config_api.py
modern_pylogging/console_formatter.py
modern_pylogging/contextvars_helpers.py
modern_pylogging/helper_types.py
modern_pylogging/helper_utils.py
modern_pylogging/import_checker.py
modern_pylogging/json_formatter.py
modern_pylogging/json_helper.py
modern_pylogging/logging_handlers.py
modern_pylogging/logging_manager.py
modern_pylogging/orjson_helper.py
modern_pylogging/picologging_handlers.py
modern_pylogging/py.typed
modern_pylogging-0.4.0.dist-info/METADATA
modern_pylogging-0.4.0.dist-info/WHEEL
modern_pylogging-0.4.0.dist-info/licenses/LICENSE
modern_pylogging-0.4.0.dist-info/RECORD
