Metadata-Version: 2.4
Name: modern_pylogging
Version: 0.4.0
Summary: Helper library for configuring python logging
Author-email: "Dmitry P." <wwarne@gmail.com>
License-File: LICENSE
Requires-Python: >=3.10
